<tests path="D:\dev\personal\TestRunner\TestBin">
  <!--<test name="Validator Simulator Test" description="Validates the datasets inserted to the database by the ValidatorSimulator."
        path="${path}" fileName="eO.Lib.Test.Integration.Business.Manager.ValidatorSimulatorManager.dll"
        typeName="eO.Lib.Test.Integration.Business.Manager.ValidatorSimulatorManager.Test"
        repeatCount="1">
    <dependency path="${path}" name="eO.Lib.Business.Entity" extension="dll">
      <typeName>eO.Lib.Business.Entity.CdCache.CdUpdateInfoEntity</typeName>
      <typeName>eO.Lib.Business.Entity.Hotlist.HotlistEntity</typeName>
    </dependency>
    <dependency path="${path}" name="eO.Lib.Data.Sql" extension="dll" typeName="eO.Lib.Data.Sql.ValidatorSimulatorHotlist.ValidatorSimulatorHotlistDac">
    </dependency>
    <dependency path="${path}" name="eO.Lib.Business.Manager" extension="dll" typeName="eO.Lib.Business.Manager.ValidatorSimulator.ValidatorSimulatorManager" />
    <dependency path="${path}" name="eO.Lib.Utility.Enum" extension="dll" typeName="eO.Lib.Utility.Enum.CdUpdateType" />
    <dependency name="AgencyName" value="UTA" />
    <dependency name="HotlistStartSequenceNumber" value="0" />
    <dependency name="ColdlistStartSequenceNumber" value="0" />
  </test>-->  
  <!--<test name="Comparator Validator Test" description="Validates the results of the Comparitor Manager against a direct database call."
        path="${path}" fileName="eO.Lib.Test.System.Business.Manager.ComparatorAutomation.ComparatorTester.dll"
        typeName="eO.Lib.Test.System.Business.Manager.ComparatorAutomation.ComparatorTester.ComparatorValidator"
        repeatCount="1">
    <dependency path="${path}" name="eO.Lib.Data.Sql" extension="dll" typeName="eO.Lib.Data.Sql.CdListItem.ColdListItemDac" />
    <dependency path="${path}" name="eO.Lib.Business.Manager" extension="dll" typeName="eO.Lib.Business.Manager.Comparator.ComparatorManager" />
    <dependency name="institutionName" value="UTA" />
    <dependency name="nameSpace" value="UTA/nameSpaceValue" />
  </test>-->  
  <!--<test name="Round Trip Client Call" description="The client calls the WCF Service which in turn calls the Web Service, and updates portions of the passed string at each level to prove that each level of the call was made."
        path="${path}" fileName="RoundTripClientCall.dll" typeName="RoundTripClientCall.ServiceRunner" repeatCount="10" />  
  <test name="Sleep Test" description="Sleeps for random time sets. This is a demo test for the test harness tool."
        path="${path}" fileName="SleepTest.dll" typeName="SleepTest.Class1"
        repeatCount="10">
    <dependency name="DATABASE_USER_NAME" value="sa" />
    <dependency name="CATALOG" value="ACH_IAT_CU" />
    <dependency name="SERVER_NAME" value="SALTQA" />
    <dependency name="PASSWORD" value="temple#1100" />
  </test>-->
  <test name="Sleep1" path="${path}" fileName="SleepTest.dll" typeName="SleepTest.Class1" repeatCount="10">
    <dependency name="dependencyA" dbuserName="sa" dbPassword="password2" />
  </test>
  <test name="Sleep2" path="${path}" fileName="SleepTest.dll" typeName="SleepTest.Class1"
        repeatCount="10"/>
  <test name="Sleep3" path="${path}" fileName="SleepTest.dll" typeName="SleepTest.Class1"
        repeatCount="10"/>
  <test name="Sleep4" path="${path}" fileName="SleepTest.dll" typeName="SleepTest.Class1"
        repeatCount="10"/>  
  <!--
  Sample Test section
  <test path="${path}" fileName="<name of the assembly>" typeName="<full class name including namespace>" repeatCount="<int indicating the number of times to execute the test>">
    dependencies can be added for use within a given test to provide custom environmental data. Custom code within the test itself will have to parse
    that dictionary and know how to use the data. 
    <dependency path="${path}" name="<name of assembly without extension>" extension="<extension of assembly>" typeName="<full class name including namespace>" />
  </test>
  -->
</tests>